final/TOPSIS.py
final/__init__.py
topsis_ritwik_102303905-0.0.2.dist-info/METADATA
topsis_ritwik_102303905-0.0.2.dist-info/WHEEL
topsis_ritwik_102303905-0.0.2.dist-info/top_level.txt
topsis_ritwik_102303905-0.0.2.dist-info/RECORD
