Metadata-Version: 2.4
Name: topsis-ritwik-102303905
Version: 0.0.2
Summary: Python project on TOPSIS
Author: Ritwik Bhandari
Author-email: rbhandari_be23@thapar.edu
Keywords: python,topsis,data ranking,numpy
Dynamic: author
Dynamic: author-email
Dynamic: description
Dynamic: description-content-type
Dynamic: keywords
Dynamic: summary
